mahjong/__init__.py
mahjong/agari.py
mahjong/constants.py
mahjong/meld.py
mahjong/py.typed
mahjong/shanten.py
mahjong/tile.py
mahjong/utils.py
mahjong/hand_calculating/__init__.py
mahjong/hand_calculating/divider.py
mahjong/hand_calculating/fu.py
mahjong/hand_calculating/hand.py
mahjong/hand_calculating/hand_config.py
mahjong/hand_calculating/hand_response.py
mahjong/hand_calculating/scores.py
mahjong/hand_calculating/yaku.py
mahjong/hand_calculating/yaku_config.py
mahjong/hand_calculating/yaku_list/__init__.py
mahjong/hand_calculating/yaku_list/aka_dora.py
mahjong/hand_calculating/yaku_list/chankan.py
mahjong/hand_calculating/yaku_list/chantai.py
mahjong/hand_calculating/yaku_list/chiitoitsu.py
mahjong/hand_calculating/yaku_list/chinitsu.py
mahjong/hand_calculating/yaku_list/chun.py
mahjong/hand_calculating/yaku_list/daburu_open_riichi.py
mahjong/hand_calculating/yaku_list/daburu_riichi.py
mahjong/hand_calculating/yaku_list/dora.py
mahjong/hand_calculating/yaku_list/east.py
mahjong/hand_calculating/yaku_list/haitei.py
mahjong/hand_calculating/yaku_list/haku.py
mahjong/hand_calculating/yaku_list/hatsu.py
mahjong/hand_calculating/yaku_list/honitsu.py
mahjong/hand_calculating/yaku_list/honroto.py
mahjong/hand_calculating/yaku_list/houtei.py
mahjong/hand_calculating/yaku_list/iipeiko.py
mahjong/hand_calculating/yaku_list/ippatsu.py
mahjong/hand_calculating/yaku_list/ittsu.py
mahjong/hand_calculating/yaku_list/junchan.py
mahjong/hand_calculating/yaku_list/nagashi_mangan.py
mahjong/hand_calculating/yaku_list/north.py
mahjong/hand_calculating/yaku_list/open_riichi.py
mahjong/hand_calculating/yaku_list/pinfu.py
mahjong/hand_calculating/yaku_list/renhou.py
mahjong/hand_calculating/yaku_list/riichi.py
mahjong/hand_calculating/yaku_list/rinshan.py
mahjong/hand_calculating/yaku_list/ryanpeiko.py
mahjong/hand_calculating/yaku_list/sanankou.py
mahjong/hand_calculating/yaku_list/sankantsu.py
mahjong/hand_calculating/yaku_list/sanshoku.py
mahjong-1.4.0.dist-info/licenses/LICENSE.txt
mahjong-1.4.0.dist-info/METADATA
mahjong-1.4.0.dist-info/WHEEL
mahjong-1.4.0.dist-info/top_level.txt
mahjong-1.4.0.dist-info/RECORD
