Metadata-Version: 2.4
Name: mahjong
Version: 1.4.0
Summary: Mahjong hands calculation
Author-email: Alexey Lisikhin <alexey@nihisil.com>
License-Expression: MIT
Project-URL: Homepage, https://github.com/MahjongRepository/mahjong
Classifier: Development Status :: 5 - Production/Stable
Classifier: Environment :: Console
Classifier: Intended Audience :: Developers
Classifier: Programming Language :: Python
Classifier: Programming Language :: Python :: 3.9
Classifier: Programming Language :: Python :: 3.10
Classifier: Programming Language :: Python :: 3.11
Classifier: Programming Language :: Python :: 3.12
Classifier: Programming Language :: Python :: 3.13
Classifier: Programming Language :: Python :: 3.14
Requires-Python: >=3.9
License-File: LICENSE.txt
Dynamic: license-file
